rajinipp/__init__.py
rajinipp/__main__.py
rajinipp/__rajiniworld__.py
rajinipp/ast/__init__.py
rajinipp/ast/base.py
rajinipp/ast/blocks.py
rajinipp/ast/control.py
rajinipp/ast/ops.py
rajinipp/execptions.py
rajinipp/lexer.py
rajinipp/parser/__init__.py
rajinipp/parser/atom_parser.py
rajinipp/parser/expr_parser.py
rajinipp/parser/flow_parser.py
rajinipp/parser/func_parser.py
rajinipp/parser/ops_parser.py
rajinipp/parser/parser.py
rajinipp/parser/print_parser.py
rajinipp/parser/stmt_parser.py
rajinipp/parser/var_parser.py
rajinipp/runner.py
rajinipp/token.yml
rajinipp/utils.py
rajinipp-0.3.1.dist-info/entry_points.txt
rajinipp-0.3.1.dist-info/LICENSE
rajinipp-0.3.1.dist-info/WHEEL
rajinipp-0.3.1.dist-info/METADATA
rajinipp-0.3.1.dist-info/RECORD
