Metadata-Version: 2.1
Name: rajinipp
Version: 0.3.1
Summary: Rajini++ (rajiniPP) is a programming language based on the iconic dialogues by Rajinikanth.
Home-page: https://github.com/aadhithya/rajiniPP
License: MIT
Keywords: esolang,interpreter,rply,rajinipp,superstar
Author: Aadhithya Sankar
Author-email: a.sankar@tum.de
Requires-Python: >=3.8,<3.11
Classifier: License :: OSI Approved :: MIT License
Classifier: Programming Language :: Python :: 3
Classifier: Programming Language :: Python :: 3.10
Classifier: Programming Language :: Python :: 3.8
Classifier: Programming Language :: Python :: 3.9
Classifier: Topic :: Software Development :: Interpreters
Classifier: Topic :: Software Development :: Libraries :: Python Modules
Requires-Dist: loguru (>=0.6.0,<0.7.0)
Requires-Dist: munch (>=2.5.0,<3.0.0)
Requires-Dist: rply (>=0.7.8,<0.8.0)
Requires-Dist: typer (>=0.4.1,<0.5.0)
Project-URL: Documentation, https://github.com/aadhithya/rajiniPP/wiki
Project-URL: Repository, https://github.com/aadhithya/rajiniPP
